HalApyJson/GLOBALS.py
HalApyJson/__init__.py
HalApyJson/api_manager.py
HalApyJson/haj_globals.py
HalApyJson/json_parser.py
HalApyJson/main.py
HalApyJson/setup.py
HalApyJson/CLI/__init__.py
HalApyJson/CLI/cli.py
HalApyJson/CONFIG/hal_config.json
HalApyJson-1.1.3.dist-info/LICENSE
HalApyJson-1.1.3.dist-info/METADATA
HalApyJson-1.1.3.dist-info/WHEEL
HalApyJson-1.1.3.dist-info/entry_points.txt
HalApyJson-1.1.3.dist-info/top_level.txt
HalApyJson-1.1.3.dist-info/RECORD
