Metadata-Version: 2.1
Name: HalApyJson
Version: 1.1.3
Summary: Python modules for parsing the response to a HAL API request
Home-page: https://github.com/Bertin-fap/HalApyJson
Author: BiblioAnalysis team
Author-email: francois.bertin7@wanadoo.fr, amal.chabli@orange.fr
License: MIT
Keywords: Metadata parsing,HAL request,API management
Platform: UNKNOWN
Classifier: Development Status :: 4 - Beta
Classifier: License :: OSI Approved :: MIT License
Classifier: Programming Language :: Python :: 3.9
Classifier: Topic :: Scientific/Engineering :: Information Analysis
Classifier: Operating System :: OS Independent
Classifier: Intended Audience :: Science/Research
License-File: LICENSE
Requires-Dist: openpyxl==3.1.2
Requires-Dist: pandas==2.1.4
Requires-Dist: requests==2.31.0
